respan_tracing/__init__.py
respan_tracing/constants/__init__.py
respan_tracing/constants/context_constants.py
respan_tracing/constants/generic_constants.py
respan_tracing/constants/respan_config.py
respan_tracing/constants/tracing.py
respan_tracing/contexts/span.py
respan_tracing/contexts/stdio.py
respan_tracing/core/__init__.py
respan_tracing/core/client.py
respan_tracing/core/tracer.py
respan_tracing/decorators/__init__.py
respan_tracing/decorators/base.py
respan_tracing/exporters/__init__.py
respan_tracing/exporters/respan.py
respan_tracing/instruments.py
respan_tracing/main.py
respan_tracing/processors/__init__.py
respan_tracing/processors/base.py
respan_tracing/utils/__init__.py
respan_tracing/utils/context.py
respan_tracing/utils/imports.py
respan_tracing/utils/instrumentation.py
respan_tracing/utils/logging.py
respan_tracing/utils/notebook.py
respan_tracing/utils/preprocessing/__init__.py
respan_tracing/utils/preprocessing/span_processing.py
respan_tracing-1.0.0.dist-info/METADATA
respan_tracing-1.0.0.dist-info/WHEEL
respan_tracing-1.0.0.dist-info/RECORD
