Metadata-Version: 2.1
Name: respan-tracing
Version: 1.0.0
Summary: Respan SDK allows you to interact with the Respan API smoothly
License: MIT
Author: Respan
Author-email: team@respan.ai
Requires-Python: >=3.11,<3.14
Classifier: License :: OSI Approved :: MIT License
Classifier: Programming Language :: Python :: 3
Classifier: Programming Language :: Python :: 3.11
Classifier: Programming Language :: Python :: 3.12
Requires-Dist: instructor (>=1.13.0,<2.0.0)
Requires-Dist: opentelemetry-api (>=1.29.0,<2.0.0)
Requires-Dist: opentelemetry-exporter-otlp (>=1.33.1,<2.0.0)
Requires-Dist: opentelemetry-instrumentation-openai (>=0.48.0,<0.49.0)
Requires-Dist: opentelemetry-instrumentation-threading (>=0.55b1,<0.56)
Requires-Dist: opentelemetry-sdk (>=1.29.0,<2.0.0)
Requires-Dist: pytest (>=8.4.1,<9.0.0)
Requires-Dist: respan-sdk (>=1.0.0,<2.0.0)
Requires-Dist: typing-extensions (>=4.12.2,<5.0.0)
